bigot/__init__.py
bigot-1.0.2.dist-info/LICENSE
bigot-1.0.2.dist-info/METADATA
bigot-1.0.2.dist-info/WHEEL
bigot-1.0.2.dist-info/top_level.txt
bigot-1.0.2.dist-info/RECORD
