Metadata-Version: 2.1
Name: bigot
Version: 1.0.2
Summary: Benchmarking library with Space and Time Complexity estimation
Home-page: https://github.com/arnaudsm/bigot
Author: Arnaud de Saint Meloir
Author-email: arnaud.desaintmeloir@gmail.com
License: UNKNOWN
Platform: UNKNOWN
Requires-Dist: memory-profiler
Requires-Dist: pandas
Requires-Dist: plotly
